robots/__init__.py
robots/android.py
robots/run.py
robots-0.1.5.dist-info/LICENSE
robots-0.1.5.dist-info/METADATA
robots-0.1.5.dist-info/WHEEL
robots-0.1.5.dist-info/entry_points.txt
robots-0.1.5.dist-info/top_level.txt
robots-0.1.5.dist-info/RECORD
