Metadata-Version: 2.1
Name: robots
Version: 0.1.5
Summary: A lightweight automation tool.
Home-page: https://ahamega.com/support
Author: leesoar
Author-email: core@111.com
License: MIT
Keywords: robots,robot,human
Platform: UNKNOWN
Classifier: License :: OSI Approved :: MIT License
Classifier: Programming Language :: Python :: 3.5
Classifier: Programming Language :: Python :: 3.6
Classifier: Programming Language :: Python :: 3.7
Classifier: Programming Language :: Python :: Implementation :: CPython
Classifier: Programming Language :: Python :: Implementation :: PyPy
Requires-Python: >=3.3.0
